{
  "Textures": {
    "PM_Diffuse": "HT/Content/CoreMaterials/Character/DefaultTextures/T_Linear_White.T_Linear_White",
    "BaseColor": "HT/Content/Characters/Player/018_alphard/ter/face_ter/T_player_018_alphard_eyes_d.T_player_018_alphard_eyes_d",
    "ID_Tex": "HT/Content/CoreMaterials/Character/DefaultTextures/T_Linear_White.T_Linear_White",
    "LightMap": "HT/Content/CoreMaterials/Character/DefaultTextures/T_Linear_White.T_Linear_White",
    "T_Linear_White": "HT/Content/CoreMaterials/Character/DefaultTextures/T_Linear_White.T_Linear_White",
    "BaseMatcap": "HT/Content/CoreMaterials/Character/DefaultTextures/T_Linear_White.T_Linear_White",
    "Matcap6": "HT/Content/CoreMaterials/Character/DefaultTextures/T_Linear_White.T_Linear_White"
  },
  "Parameters": {
    "BlendMode": 1,
    "ShadingModel": 0,
    "Colors": {
      "BaseColor": {
        "R": 1.0,
        "G": 1.0,
        "B": 1.0,
        "A": 1.0,
        "Hex": "FFFFFF"
      },
      "ShadowColor": {
        "R": 0.8,
        "G": 0.8,
        "B": 0.8,
        "A": 1.0,
        "Hex": "E8E8E8"
      },
      "HairShadow_WorldOffset": {
        "R": 0.0,
        "G": -0.0,
        "B": 0.0,
        "A": 1.0,
        "Hex": "000000"
      }
    },
    "Scalars": {
      "OffsetStrength": 1.0,
      "Opacity": 1.0,
      "RampID": 2.0,
      "ToonID": 0.0,
      "BaseMatcapMin": 1.0,
      "BaseMatcapMax": 1.0,
      "BaseMatcapInt": 0.0,
      "RampID1": 0.0,
      "RampID2": 0.0,
      "RampID5": 0.0,
      "Matcap6Min": 0.0,
      "Matcap6Max": 0.0,
      "Matcap6Int": 0.0,
      "RampID6": 0.0,
      "SpecSize": 0.0,
      "SpecIntensity": 0.0,
      "RefractionDepthBias": 0.0
    },
    "Switches": {},
    "Properties": {
      "bOverrideOutlineOverlayMaterial": true,
      "OutlineOverlayMaterial": {
        "ObjectName": "MaterialInstanceConstant'MI_018_OutLine'",
        "ObjectPath": "HT/Content/Characters/Player/018_alphard/ter/outline/MI_018_OutLine.0"
      },
      "BasePropertyOverrides": {
        "BlendMode": "EBlendMode::BLEND_Masked",
        "ShadingModel": "EMaterialShadingModel::MSM_Toon",
        "OpacityMaskClipValue": 0.3333
      },
      "bIncludedInBaseGame": true
    },
    "HasTopDiffuse": true,
    "HasTopNormals": false,
    "HasTopSpecularMasks": false,
    "HasTopEmissive": false,
    "IsTranslucent": false,
    "IsNull": false
  }
}